README
setup.cfg
setup.py
cleverbot_io/__init__.py
cleverbot_io.egg-info/PKG-INFO
cleverbot_io.egg-info/SOURCES.txt
cleverbot_io.egg-info/dependency_links.txt
cleverbot_io.egg-info/requires.txt
cleverbot_io.egg-info/top_level.txt