Metadata-Version: 1.0
Name: cleverbot-io
Version: 1.0.1
Summary: An unofficial Python wrapper for Cleverbot.io
Home-page: http://www.cleverbot.io
Author: Underforest
Author-email: neovisatoons@gmail.com
License: MIT
Platform: UNKNOWN
